globlexgptai/__init__.py
globlexgptai/__main__.py
globlexgptai/chutes.py
globlexgptai/client.py
globlexgptai/ollama.py
globlexgptai-1.0.1.dist-info/METADATA
globlexgptai-1.0.1.dist-info/WHEEL
globlexgptai-1.0.1.dist-info/top_level.txt
globlexgptai-1.0.1.dist-info/RECORD
