Metadata-Version: 2.4
Name: GlobleXGPTAi
Version: 1.0.1
Summary: GlobleXGPTAi Model Python Client (Multi-Provider Support) developed by Himanshu
Home-page: https://github.com/heyhimanshu/globle-gpt
Author: Himanshu
Author-email: Himanshu <your-email@example.com>
Project-URL: Homepage, https://github.com/heyhimanshu/globle-gpt
Classifier: Programming Language :: Python :: 3
Classifier: License :: OSI Approved :: MIT License
Classifier: Operating System :: OS Independent
Requires-Python: >=3.6
Requires-Dist: requests
Dynamic: author
Dynamic: home-page
Dynamic: requires-python
